{"id":"IL-050025600000000","structureNumber":"050025600000000","state":"IL","stateFips":"17","stateName":"Illinois","countyFips":"099","placeFips":"04245","location":"2.2 MI S OF US 6","featuresIntersected":"ILLINOIS RIVER","facilityCarried":"ILL 178","lat":42.410278,"lon":-90.0525,"routePrefix":"3","routePrefixName":"State Highway","routeNumber":"178","owner":"01","ownerName":"State Highway Agency","functionalClass":"07","yearBuilt":2020,"yearReconstructed":null,"material":"4","materialName":"Steel Continuous","materialGroup":"Steel","designType":"02","designTypeName":"Stringer/Multi-beam or Girder","lanesOn":2,"lanesUnder":0,"maxSpanM":13.4,"maxSpanFt":44.0,"lengthM":35.3,"lengthFt":115.9,"deckWidthM":1.5,"deckWidthFt":5.0,"roadwayWidthM":1.1,"adt":3200,"adtYear":2023,"truckPct":8,"futureAdt":3586,"deckCondition":"8","superstructureCondition":"8","substructureCondition":"7","culvertCondition":null,"channelCondition":"9","lowestRating":7,"conditionCategory":"good","structurallyDeficient":false,"operatingRating":6.1,"inventoryRating":4.7,"toll":false,"historical":"5","historicalName":"Not eligible","scourCritical":"8","detourKm":13,"status":"A","deckArea":5371.7}