{"id":"IL-082992900000000","structureNumber":"082992900000000","state":"IL","stateFips":"17","stateName":"Illinois","countyFips":"163","placeFips":"01660","location":"E ST LOUIS","featuresIntersected":"MISS RIV/RR/MSS6000","facilityCarried":"FAU 9187A & MET LI","lat":39.841389,"lon":-91.368333,"routePrefix":"8","routePrefixName":"Other","routeNumber":"0","owner":"26","ownerName":"Private","functionalClass":"16","yearBuilt":1874,"yearReconstructed":2003,"material":"3","materialName":"Steel","materialGroup":"Steel","designType":"00","designTypeName":"Other","lanesOn":4,"lanesUnder":2,"maxSpanM":15.8,"maxSpanFt":52.0,"lengthM":122.1,"lengthFt":400.7,"deckWidthM":1.7,"deckWidthFt":5.4,"roadwayWidthM":1.4,"adt":6550,"adtYear":2023,"truckPct":6,"futureAdt":14746,"deckCondition":"6","superstructureCondition":"5","substructureCondition":"5","culvertCondition":null,"channelCondition":"6","lowestRating":5,"conditionCategory":"fair","structurallyDeficient":false,"operatingRating":8.9,"inventoryRating":8.9,"toll":false,"historical":"1","historicalName":"On National Register of Historic Places","scourCritical":"3","detourKm":3,"status":"A","deckArea":20273.6}