{"id":"MD-100000020053010","structureNumber":"100000020053010","state":"MD","stateFips":"24","stateName":"Maryland","countyFips":"003","placeFips":"01600","location":"ANNAPOLIS MD.","featuresIntersected":"SPA CREEK","facilityCarried":"MD 181(SIXTH ST)","lat":39.566944,"lon":-76.700278,"routePrefix":"5","routePrefixName":"City Street","routeNumber":"292","owner":"01","ownerName":"State Highway Agency","functionalClass":"16","yearBuilt":1946,"yearReconstructed":null,"material":"3","materialName":"Steel","materialGroup":"Steel","designType":"16","designTypeName":"Movable - Bascule","lanesOn":2,"lanesUnder":0,"maxSpanM":1.9,"maxSpanFt":6.2,"lengthM":25.4,"lengthFt":83.2,"deckWidthM":1.2,"deckWidthFt":3.9,"roadwayWidthM":0.8,"adt":19251,"adtYear":2009,"truckPct":5,"futureAdt":28877,"deckCondition":"5","superstructureCondition":"5","substructureCondition":"6","culvertCondition":null,"channelCondition":"8","lowestRating":5,"conditionCategory":"fair","structurallyDeficient":false,"operatingRating":3.6,"inventoryRating":2.4,"toll":false,"historical":"3","historicalName":"Possibly eligible","scourCritical":"8","detourKm":6,"status":"A","deckArea":3017.8}