{"id":"MD-300000AAZ050013","structureNumber":"300000AAZ050013","state":"MD","stateFips":"24","stateName":"Maryland","countyFips":"003","placeFips":"02275","location":"6 MI E OF MD RTE 2","featuresIntersected":"CHESAPEAKE BAY","facilityCarried":"US RTE 50  EB","lat":39.836389,"lon":-76.815833,"routePrefix":"2","routePrefixName":"US Highway","routeNumber":"5","owner":"31","ownerName":"State Toll Authority","functionalClass":"12","yearBuilt":1951,"yearReconstructed":1988,"material":"3","materialName":"Steel","materialGroup":"Steel","designType":"13","designTypeName":"Suspension","lanesOn":2,"lanesUnder":0,"maxSpanM":48.8,"maxSpanFt":160.0,"lengthM":648.9,"lengthFt":2128.9,"deckWidthM":0.9,"deckWidthFt":3.1,"roadwayWidthM":0.8,"adt":38923,"adtYear":2023,"truckPct":8,"futureAdt":44600,"deckCondition":"6","superstructureCondition":"6","substructureCondition":"6","culvertCondition":null,"channelCondition":"8","lowestRating":6,"conditionCategory":"fair","structurallyDeficient":false,"operatingRating":4.5,"inventoryRating":2.6,"toll":true,"historical":"4","historicalName":"Not determined","scourCritical":"5","detourKm":2,"status":"A","deckArea":61644.6}