{"id":"OK-257860000000000","structureNumber":"257860000000000","state":"OK","stateFips":"40","stateName":"Oklahoma","countyFips":"083","placeFips":"00000","location":"I-35/US 77 JCT.","featuresIntersected":"I-35 UNDER","facilityCarried":"U.S. 77 RAMP W-N","lat":36.091944,"lon":-99.000833,"routePrefix":"2","routePrefixName":"US Highway","routeNumber":"77","owner":"01","ownerName":"State Highway Agency","functionalClass":"06","yearBuilt":2001,"yearReconstructed":null,"material":"5","materialName":"Prestressed Concrete","materialGroup":"Prestressed Concrete","designType":"02","designTypeName":"Stringer/Multi-beam or Girder","lanesOn":1,"lanesUnder":5,"maxSpanM":3.3,"maxSpanFt":10.8,"lengthM":16.2,"lengthFt":53.1,"deckWidthM":1.0,"deckWidthFt":3.1,"roadwayWidthM":0.9,"adt":13600,"adtYear":2022,"truckPct":16,"futureAdt":21760,"deckCondition":"7","superstructureCondition":"8","substructureCondition":"6","culvertCondition":null,"channelCondition":null,"lowestRating":6,"conditionCategory":"fair","structurallyDeficient":false,"operatingRating":9.7,"inventoryRating":3.7,"toll":false,"historical":"5","historicalName":"Not eligible","scourCritical":"N","detourKm":5,"status":"A","deckArea":1554.2}