{"id":"OR-08899 000 00000","structureNumber":"08899 000 00000","state":"OR","stateFips":"41","stateName":"Oregon","countyFips":"019","placeFips":"63650","location":"0.2 MI E OF I-5","featuresIntersected":"SOUTH UMPQUA RIVER","facilityCarried":"OR 138 (HWY 138)WB","lat":44.416944,"lon":-124.951944,"routePrefix":"3","routePrefixName":"State Highway","routeNumber":"138","owner":"01","ownerName":"State Highway Agency","functionalClass":"14","yearBuilt":1961,"yearReconstructed":null,"material":"2","materialName":"Concrete Continuous","materialGroup":"Concrete","designType":"05","designTypeName":"Box Beam - Multiple","lanesOn":2,"lanesUnder":0,"maxSpanM":4.9,"maxSpanFt":16.0,"lengthM":27.7,"lengthFt":90.8,"deckWidthM":1.2,"deckWidthFt":3.8,"roadwayWidthM":0.9,"adt":9117,"adtYear":2020,"truckPct":5,"futureAdt":11500,"deckCondition":"6","superstructureCondition":"6","substructureCondition":"7","culvertCondition":null,"channelCondition":"7","lowestRating":6,"conditionCategory":"fair","structurallyDeficient":false,"operatingRating":2.6,"inventoryRating":2.0,"toll":false,"historical":"5","historicalName":"Not eligible","scourCritical":"8","detourKm":null,"status":"A","deckArea":3238.6}