{"id":"NJ-0703153","structureNumber":"0703153","state":"NJ","stateFips":"34","stateName":"New Jersey","countyFips":"013","placeFips":"51000","location":"0.6 MI NW I-78&US1&9 JCT","featuresIntersected":"CONRAIL & WHEELER PT. RD","facilityCarried":"SOUTH STREET","lat":40.851111,"lon":-75.14,"routePrefix":"5","routePrefixName":"City Street","routeNumber":"0","owner":"01","ownerName":"State Highway Agency","functionalClass":"16","yearBuilt":1996,"yearReconstructed":null,"material":"4","materialName":"Steel Continuous","materialGroup":"Steel","designType":"02","designTypeName":"Stringer/Multi-beam or Girder","lanesOn":4,"lanesUnder":2,"maxSpanM":3.4,"maxSpanFt":11.2,"lengthM":24.0,"lengthFt":78.8,"deckWidthM":1.8,"deckWidthFt":5.8,"roadwayWidthM":1.5,"adt":40421,"adtYear":2023,"truckPct":4,"futureAdt":49314,"deckCondition":"7","superstructureCondition":"7","substructureCondition":"7","culvertCondition":null,"channelCondition":null,"lowestRating":7,"conditionCategory":"good","structurallyDeficient":false,"operatingRating":3.9,"inventoryRating":2.4,"toll":false,"historical":"5","historicalName":"Not eligible","scourCritical":"N","detourKm":5,"status":"A","deckArea":4251.5}