{"id":"NJ-361491A","structureNumber":"361491A","state":"NJ","stateFips":"34","stateName":"New Jersey","countyFips":"013","placeFips":"06250","location":"2 MI N OF GSP&RT280 JCT","featuresIntersected":"JFK Dr. SB & NJ TRANSIT","facilityCarried":"GSP SB ENTR. RAMP","lat":41.1525,"lon":-75.807778,"routePrefix":"8","routePrefixName":"Other","routeNumber":"GSP","owner":"31","ownerName":"State Toll Authority","functionalClass":"12","yearBuilt":1964,"yearReconstructed":null,"material":"1","materialName":"Concrete","materialGroup":"Concrete","designType":"01","designTypeName":"Slab","lanesOn":1,"lanesUnder":1,"maxSpanM":5.1,"maxSpanFt":16.6,"lengthM":22.2,"lengthFt":73.0,"deckWidthM":0.7,"deckWidthFt":2.4,"roadwayWidthM":0.6,"adt":19484,"adtYear":2022,"truckPct":1,"futureAdt":23774,"deckCondition":"6","superstructureCondition":"5","substructureCondition":"6","culvertCondition":null,"channelCondition":null,"lowestRating":5,"conditionCategory":"fair","structurallyDeficient":false,"operatingRating":3.1,"inventoryRating":2.4,"toll":true,"historical":"5","historicalName":"Not eligible","scourCritical":"N","detourKm":2,"status":"A","deckArea":1624.2}