{"id":"AL-019120","structureNumber":"019120","state":"AL","stateFips":"01","stateName":"Alabama","countyFips":"109","placeFips":"01109","location":"SEC19 T10N R19E","featuresIntersected":"PATSALIGA CREEK","facilityCarried":"COUNTY ROAD 1170","lat":33.346667,"lon":-87.787222,"routePrefix":"4","routePrefixName":"County Road","routeNumber":"3","owner":"02","ownerName":"County Highway Agency","functionalClass":"07","yearBuilt":2004,"yearReconstructed":null,"material":"5","materialName":"Prestressed Concrete","materialGroup":"Prestressed Concrete","designType":"02","designTypeName":"Stringer/Multi-beam or Girder","lanesOn":2,"lanesUnder":0,"maxSpanM":2.6,"maxSpanFt":8.5,"lengthM":22.2,"lengthFt":73.0,"deckWidthM":0.8,"deckWidthFt":2.8,"roadwayWidthM":0.8,"adt":400,"adtYear":2003,"truckPct":6,"futureAdt":595,"deckCondition":"7","superstructureCondition":"8","substructureCondition":"8","culvertCondition":null,"channelCondition":"8","lowestRating":7,"conditionCategory":"good","structurallyDeficient":false,"operatingRating":6.0,"inventoryRating":3.6,"toll":false,"historical":"5","historicalName":"Not eligible","scourCritical":"8","detourKm":24,"status":"A","deckArea":1891.2}