{"id":"AL-021486","structureNumber":"021486","state":"AL","stateFips":"01","stateName":"Alabama","countyFips":"017","placeFips":"00000","location":"0.1 MI E OF WEST POINT","featuresIntersected":"CHATTAHOOCHEE RIVER","facilityCarried":"I-85 (SBL)","lat":33.376944,"lon":-86.309167,"routePrefix":"1","routePrefixName":"Interstate","routeNumber":"85","owner":"01","ownerName":"State Highway Agency","functionalClass":"01","yearBuilt":1961,"yearReconstructed":2005,"material":"4","materialName":"Steel Continuous","materialGroup":"Steel","designType":"02","designTypeName":"Stringer/Multi-beam or Girder","lanesOn":2,"lanesUnder":0,"maxSpanM":3.0,"maxSpanFt":10.0,"lengthM":33.1,"lengthFt":108.6,"deckWidthM":1.4,"deckWidthFt":4.6,"roadwayWidthM":1.3,"adt":44900,"adtYear":2020,"truckPct":19,"futureAdt":50685,"deckCondition":"7","superstructureCondition":"7","substructureCondition":"6","culvertCondition":null,"channelCondition":"7","lowestRating":6,"conditionCategory":"fair","structurallyDeficient":false,"operatingRating":4.4,"inventoryRating":2.6,"toll":false,"historical":"5","historicalName":"Not eligible","scourCritical":"5","detourKm":2,"status":"A","deckArea":4600.9}