{"id":"WA-0007565B0000000","structureNumber":"0007565B0000000","state":"WA","stateFips":"53","stateName":"Washington","countyFips":"033","placeFips":"00000","location":"JCT I-5","featuresIntersected":"I-5","facilityCarried":"I-90 W-S RAMP","lat":48.636111,"lon":-122.636111,"routePrefix":"1","routePrefixName":"Interstate","routeNumber":"9","owner":"01","ownerName":"State Highway Agency","functionalClass":"11","yearBuilt":1965,"yearReconstructed":1988,"material":"2","materialName":"Concrete Continuous","materialGroup":"Concrete","designType":"05","designTypeName":"Box Beam - Multiple","lanesOn":1,"lanesUnder":10,"maxSpanM":2.6,"maxSpanFt":8.6,"lengthM":38.0,"lengthFt":124.5,"deckWidthM":0.8,"deckWidthFt":2.6,"roadwayWidthM":0.6,"adt":19205,"adtYear":2012,"truckPct":5,"futureAdt":32111,"deckCondition":"7","superstructureCondition":"7","substructureCondition":"7","culvertCondition":null,"channelCondition":null,"lowestRating":7,"conditionCategory":"good","structurallyDeficient":false,"operatingRating":2.8,"inventoryRating":2.0,"toll":false,"historical":"5","historicalName":"Not eligible","scourCritical":"N","detourKm":6,"status":"A","deckArea":2960.1}