{"id":"AZ-02616","structureNumber":"02616","state":"AZ","stateFips":"04","stateName":"Arizona","countyFips":"013","placeFips":"55000","location":"0.25 mi W of L101/L202","featuresIntersected":"SR 202L  Ramps A  B","facilityCarried":"Ramp E-N","lat":34.12,"lon":-113.2,"routePrefix":"3","routePrefixName":"State Highway","routeNumber":"101","owner":"01","ownerName":"State Highway Agency","functionalClass":"12","yearBuilt":2004,"yearReconstructed":null,"material":"6","materialName":"Prestressed Concrete Continuous","materialGroup":"Prestressed Concrete","designType":"06","designTypeName":"Box Beam - Single/Spread","lanesOn":1,"lanesUnder":10,"maxSpanM":5.8,"maxSpanFt":18.9,"lengthM":19.5,"lengthFt":63.9,"deckWidthM":0.9,"deckWidthFt":3.1,"roadwayWidthM":0.8,"adt":11478,"adtYear":2021,"truckPct":7,"futureAdt":11488,"deckCondition":"7","superstructureCondition":"7","substructureCondition":"7","culvertCondition":null,"channelCondition":null,"lowestRating":7,"conditionCategory":"good","structurallyDeficient":false,"operatingRating":8.2,"inventoryRating":4.6,"toll":false,"historical":"5","historicalName":"Not eligible","scourCritical":"N","detourKm":10,"status":"A","deckArea":1850.6}