{"id":"CA-04C0239","structureNumber":"04C0239","state":"CA","stateFips":"06","stateName":"California","countyFips":"023","placeFips":"00000","location":"OLD SMITH POINT","featuresIntersected":"SOUTH FORK EEL RIVER","facilityCarried":"SMITH POINT","lat":41.5675,"lon":-124.914722,"routePrefix":"4","routePrefixName":"County Road","routeNumber":"0","owner":"02","ownerName":"County Highway Agency","functionalClass":"09","yearBuilt":1934,"yearReconstructed":null,"material":"4","materialName":"Steel Continuous","materialGroup":"Steel","designType":"02","designTypeName":"Stringer/Multi-beam or Girder","lanesOn":2,"lanesUnder":0,"maxSpanM":3.7,"maxSpanFt":12.0,"lengthM":16.9,"lengthFt":55.5,"deckWidthM":0.8,"deckWidthFt":2.8,"roadwayWidthM":0.7,"adt":69,"adtYear":2010,"truckPct":1,"futureAdt":102,"deckCondition":"5","superstructureCondition":"7","substructureCondition":"5","culvertCondition":null,"channelCondition":"6","lowestRating":5,"conditionCategory":"fair","structurallyDeficient":false,"operatingRating":6.0,"inventoryRating":3.6,"toll":false,"historical":"2","historicalName":"Eligible for NRHP","scourCritical":"3","detourKm":6,"status":"A","deckArea":1421.3}