{"id":"CA-24 0390","structureNumber":"24 0390","state":"CA","stateFips":"06","stateName":"California","countyFips":"067","placeFips":"00000","location":"03-SAC-099-7.92","featuresIntersected":"CONSUMNES RIVER OVERFLOW","facilityCarried":"STATE ROUTE 99","lat":38.464444,"lon":-121.963056,"routePrefix":"3","routePrefixName":"State Highway","routeNumber":"99","owner":"01","ownerName":"State Highway Agency","functionalClass":"02","yearBuilt":2022,"yearReconstructed":null,"material":"6","materialName":"Prestressed Concrete Continuous","materialGroup":"Prestressed Concrete","designType":"02","designTypeName":"Stringer/Multi-beam or Girder","lanesOn":6,"lanesUnder":0,"maxSpanM":3.9,"maxSpanFt":12.9,"lengthM":20.3,"lengthFt":66.7,"deckWidthM":3.6,"deckWidthFt":11.7,"roadwayWidthM":3.4,"adt":84000,"adtYear":2019,"truckPct":18,"futureAdt":109200,"deckCondition":"7","superstructureCondition":"7","substructureCondition":"7","culvertCondition":null,"channelCondition":"7","lowestRating":7,"conditionCategory":"good","structurallyDeficient":false,"operatingRating":5.4,"inventoryRating":3.2,"toll":false,"historical":"5","historicalName":"Not eligible","scourCritical":"8","detourKm":23,"status":"A","deckArea":7281.7}