{"id":"CA-56 0687G","structureNumber":"56 0687G","state":"CA","stateFips":"06","stateName":"California","countyFips":"065","placeFips":"00000","location":"08-RIV-060-R0.44","featuresIntersected":"ROUTE 15 & ROUTE 60","facilityCarried":"E60-N15 CONNECTOR","lat":34.516944,"lon":-117.782778,"routePrefix":"2","routePrefixName":"US Highway","routeNumber":"6","owner":"01","ownerName":"State Highway Agency","functionalClass":"12","yearBuilt":1979,"yearReconstructed":null,"material":"6","materialName":"Prestressed Concrete Continuous","materialGroup":"Prestressed Concrete","designType":"05","designTypeName":"Box Beam - Multiple","lanesOn":2,"lanesUnder":19,"maxSpanM":5.2,"maxSpanFt":17.1,"lengthM":36.9,"lengthFt":121.0,"deckWidthM":1.3,"deckWidthFt":4.2,"roadwayWidthM":1.2,"adt":16500,"adtYear":2020,"truckPct":18,"futureAdt":20403,"deckCondition":"5","superstructureCondition":"5","substructureCondition":"7","culvertCondition":null,"channelCondition":null,"lowestRating":5,"conditionCategory":"fair","structurallyDeficient":false,"operatingRating":10.0,"inventoryRating":3.2,"toll":false,"historical":"5","historicalName":"Not eligible","scourCritical":"N","detourKm":null,"status":"A","deckArea":4721.9}