{"id":"CA-57C0887L","structureNumber":"57C0887L","state":"CA","stateFips":"06","stateName":"California","countyFips":"073","placeFips":"66000","location":"300 FT N/O ROUTE 8","featuresIntersected":"SAN DIEGO RIVER","facilityCarried":"S/B MISSION BAY DR","lat":33.519444,"lon":-117.975,"routePrefix":"5","routePrefixName":"City Street","routeNumber":"0","owner":"04","ownerName":"City/Municipal","functionalClass":"14","yearBuilt":2023,"yearReconstructed":null,"material":"2","materialName":"Concrete Continuous","materialGroup":"Concrete","designType":"05","designTypeName":"Box Beam - Multiple","lanesOn":3,"lanesUnder":0,"maxSpanM":6.1,"maxSpanFt":20.0,"lengthM":39.6,"lengthFt":129.9,"deckWidthM":2.3,"deckWidthFt":7.4,"roadwayWidthM":1.4,"adt":55000,"adtYear":2020,"truckPct":1,"futureAdt":64343,"deckCondition":"7","superstructureCondition":"7","substructureCondition":"7","culvertCondition":null,"channelCondition":"9","lowestRating":7,"conditionCategory":"good","structurallyDeficient":false,"operatingRating":5.4,"inventoryRating":3.2,"toll":false,"historical":"5","historicalName":"Not eligible","scourCritical":"5","detourKm":2,"status":"A","deckArea":8949.6}