{"id":"AK-E09211T0735-010","structureNumber":"E09211T0735-010","state":"AK","stateFips":"02","stateName":"Alaska","countyFips":"198","placeFips":"00000","location":"3.0 MILES EAST OF HYDABUR","featuresIntersected":"SUKKWAN STRAIT","facilityCarried":"IRR BIA RTE 735","lat":55.371944,"lon":-133.710556,"routePrefix":"6","routePrefixName":"Federal Lands","routeNumber":"735","owner":"61","ownerName":"Tribal","functionalClass":"09","yearBuilt":1970,"yearReconstructed":1981,"material":"1","materialName":"Concrete","materialGroup":"Concrete","designType":"05","designTypeName":"Box Beam - Multiple","lanesOn":2,"lanesUnder":0,"maxSpanM":0.6,"maxSpanFt":2.0,"lengthM":15.3,"lengthFt":50.3,"deckWidthM":1.5,"deckWidthFt":4.8,"roadwayWidthM":1.4,"adt":5,"adtYear":2021,"truckPct":null,"futureAdt":12,"deckCondition":"4","superstructureCondition":"4","substructureCondition":"4","culvertCondition":null,"channelCondition":"8","lowestRating":4,"conditionCategory":"poor","structurallyDeficient":true,"operatingRating":0.3,"inventoryRating":null,"toll":false,"historical":"5","historicalName":"Not eligible","scourCritical":"6","detourKm":199,"status":"B","deckArea":2236.7}