{"id":"KY-104*0127*S0001","structureNumber":"104*0127*S0001","state":"KY","stateFips":"21","stateName":"Kentucky","countyFips":"207","placeFips":"00000","location":"1OMI SW OF JAMESTOWN KY.","featuresIntersected":"CUMB RIVER-WOLFCREEK DAM","facilityCarried":"US 127-US00127-0","lat":37.033333,"lon":-86.633333,"routePrefix":"2","routePrefixName":"US Highway","routeNumber":"127","owner":"70","ownerName":"Corps of Engineers","functionalClass":"02","yearBuilt":1951,"yearReconstructed":null,"material":"3","materialName":"Steel","materialGroup":"Steel","designType":"03","designTypeName":"Girder and Floorbeam","lanesOn":2,"lanesUnder":0,"maxSpanM":1.6,"maxSpanFt":5.2,"lengthM":18.3,"lengthFt":60.0,"deckWidthM":1.0,"deckWidthFt":3.2,"roadwayWidthM":0.7,"adt":1510,"adtYear":2017,"truckPct":7,"futureAdt":1800,"deckCondition":"5","superstructureCondition":"6","substructureCondition":"6","culvertCondition":null,"channelCondition":"9","lowestRating":5,"conditionCategory":"fair","structurallyDeficient":false,"operatingRating":4.3,"inventoryRating":3.3,"toll":false,"historical":"4","historicalName":"Not determined","scourCritical":"8","detourKm":97,"status":"A","deckArea":1792.4}