{"id":"PR-028661","structureNumber":"028661","state":"PR","stateFips":"72","stateName":"Puerto Rico","countyFips":"077","placeFips":"39574","location":"2 KM. N.W. OF JUNCOS.","featuresIntersected":"GURABO RIVER","facilityCarried":"C. PR-185 T0 PR-31","lat":18.957778,"lon":-66.883611,"routePrefix":"3","routePrefixName":"State Highway","routeNumber":"0","owner":"01","ownerName":"State Highway Agency","functionalClass":"07","yearBuilt":2007,"yearReconstructed":null,"material":"5","materialName":"Prestressed Concrete","materialGroup":"Prestressed Concrete","designType":"02","designTypeName":"Stringer/Multi-beam or Girder","lanesOn":2,"lanesUnder":0,"maxSpanM":3.9,"maxSpanFt":12.9,"lengthM":38.3,"lengthFt":125.8,"deckWidthM":1.5,"deckWidthFt":5.0,"roadwayWidthM":1.4,"adt":8400,"adtYear":2017,"truckPct":5,"futureAdt":11400,"deckCondition":"7","superstructureCondition":"7","substructureCondition":"4","culvertCondition":null,"channelCondition":"4","lowestRating":4,"conditionCategory":"poor","structurallyDeficient":true,"operatingRating":10.0,"inventoryRating":8.1,"toll":false,"historical":"5","historicalName":"Not eligible","scourCritical":"4","detourKm":1,"status":"A","deckArea":5827.7}