{"id":"MT-P00010045+08371","structureNumber":"P00010045+08371","state":"MT","stateFips":"30","stateName":"Montana","countyFips":"015","placeFips":"00000","location":"6M SW LOMA","featuresIntersected":"ABANDONED RAILROAD","facilityCarried":"US 87","lat":48.965278,"lon":-110.607222,"routePrefix":"2","routePrefixName":"US Highway","routeNumber":"87","owner":"01","ownerName":"State Highway Agency","functionalClass":"02","yearBuilt":1974,"yearReconstructed":null,"material":"3","materialName":"Steel","materialGroup":"Steel","designType":"02","designTypeName":"Stringer/Multi-beam or Girder","lanesOn":2,"lanesUnder":0,"maxSpanM":2.6,"maxSpanFt":8.6,"lengthM":16.1,"lengthFt":52.8,"deckWidthM":1.4,"deckWidthFt":4.7,"roadwayWidthM":1.3,"adt":1667,"adtYear":2022,"truckPct":10,"futureAdt":1750,"deckCondition":"7","superstructureCondition":"5","substructureCondition":"8","culvertCondition":null,"channelCondition":null,"lowestRating":5,"conditionCategory":"fair","structurallyDeficient":false,"operatingRating":4.2,"inventoryRating":2.2,"toll":false,"historical":"5","historicalName":"Not eligible","scourCritical":"N","detourKm":183,"status":"A","deckArea":2284.8}