{"id":"VT-200091024N13142","structureNumber":"200091024N13142","state":"VT","stateFips":"50","stateName":"Vermont","countyFips":"025","placeFips":"60250","location":"0.3 MI N EXIT 6","featuresIntersected":"I 91 OVER GM RR WLMSR","facilityCarried":"I 00091 ML","lat":44.811667,"lon":-73.7375,"routePrefix":"1","routePrefixName":"Interstate","routeNumber":"91","owner":"01","ownerName":"State Highway Agency","functionalClass":"01","yearBuilt":2019,"yearReconstructed":null,"material":"6","materialName":"Prestressed Concrete Continuous","materialGroup":"Prestressed Concrete","designType":"02","designTypeName":"Stringer/Multi-beam or Girder","lanesOn":2,"lanesUnder":0,"maxSpanM":7.5,"maxSpanFt":24.5,"lengthM":26.3,"lengthFt":86.3,"deckWidthM":1.2,"deckWidthFt":4.1,"roadwayWidthM":1.2,"adt":15000,"adtYear":2018,"truckPct":12,"futureAdt":15750,"deckCondition":"8","superstructureCondition":"8","substructureCondition":"8","culvertCondition":null,"channelCondition":"8","lowestRating":8,"conditionCategory":"good","structurallyDeficient":false,"operatingRating":4.2,"inventoryRating":3.3,"toll":false,"historical":"5","historicalName":"Not eligible","scourCritical":"8","detourKm":2,"status":"A","deckArea":3287.5}