{"id":"LA-023604509001162","structureNumber":"023604509001162","state":"LA","stateFips":"22","stateName":"Louisiana","countyFips":"071","placeFips":"55000","location":"4.5 MI NW  MISSISSIPPI R.","featuresIntersected":"METAIRIE ROAD","facilityCarried":"I0010","lat":31.301944,"lon":-91.419722,"routePrefix":"1","routePrefixName":"Interstate","routeNumber":"1","owner":"01","ownerName":"State Highway Agency","functionalClass":"11","yearBuilt":1962,"yearReconstructed":null,"material":"3","materialName":"Steel","materialGroup":"Steel","designType":"02","designTypeName":"Stringer/Multi-beam or Girder","lanesOn":3,"lanesUnder":6,"maxSpanM":2.7,"maxSpanFt":9.0,"lengthM":41.5,"lengthFt":136.0,"deckWidthM":2.1,"deckWidthFt":7.1,"roadwayWidthM":2.0,"adt":1600,"adtYear":2021,"truckPct":25,"futureAdt":1760,"deckCondition":"6","superstructureCondition":"7","substructureCondition":"7","culvertCondition":null,"channelCondition":null,"lowestRating":6,"conditionCategory":"fair","structurallyDeficient":false,"operatingRating":5.4,"inventoryRating":3.3,"toll":false,"historical":"5","historicalName":"Not eligible","scourCritical":"N","detourKm":null,"status":"A","deckArea":8911.8}