{"id":"TX-022200000813424","structureNumber":"022200000813424","state":"TX","stateFips":"48","stateName":"Texas","countyFips":"439","placeFips":"27000","location":"IH-20 & IH-35","featuresIntersected":"IH35W; IH20; SYCAMORE CK","facilityCarried":"IH20WBML/IH35WSBML","lat":34.295833,"lon":-97.805,"routePrefix":"1","routePrefixName":"Interstate","routeNumber":"2","owner":"01","ownerName":"State Highway Agency","functionalClass":"11","yearBuilt":1990,"yearReconstructed":null,"material":"4","materialName":"Steel Continuous","materialGroup":"Steel","designType":"02","designTypeName":"Stringer/Multi-beam or Girder","lanesOn":2,"lanesUnder":19,"maxSpanM":6.3,"maxSpanFt":20.6,"lengthM":112.3,"lengthFt":368.5,"deckWidthM":1.0,"deckWidthFt":3.2,"roadwayWidthM":0.9,"adt":16240,"adtYear":2013,"truckPct":1,"futureAdt":22740,"deckCondition":"7","superstructureCondition":"7","substructureCondition":"6","culvertCondition":null,"channelCondition":"8","lowestRating":6,"conditionCategory":"fair","structurallyDeficient":false,"operatingRating":4.8,"inventoryRating":2.9,"toll":false,"historical":"5","historicalName":"Not eligible","scourCritical":"8","detourKm":null,"status":"A","deckArea":11007.4}