{"id":"TX-121020017809064","structureNumber":"121020017809064","state":"TX","stateFips":"48","stateName":"Texas","countyFips":"201","placeFips":"35000","location":"0.2 MI S OF IH 45","featuresIntersected":"ELGIN ST","facilityCarried":"SP 5 NB","lat":30.7325,"lon":-95.735556,"routePrefix":"3","routePrefixName":"State Highway","routeNumber":"35","owner":"01","ownerName":"State Highway Agency","functionalClass":"12","yearBuilt":1999,"yearReconstructed":null,"material":"5","materialName":"Prestressed Concrete","materialGroup":"Prestressed Concrete","designType":"02","designTypeName":"Stringer/Multi-beam or Girder","lanesOn":4,"lanesUnder":7,"maxSpanM":3.8,"maxSpanFt":12.5,"lengthM":18.1,"lengthFt":59.5,"deckWidthM":2.3,"deckWidthFt":7.4,"roadwayWidthM":2.1,"adt":40000,"adtYear":2014,"truckPct":7,"futureAdt":31000,"deckCondition":"7","superstructureCondition":"7","substructureCondition":"7","culvertCondition":null,"channelCondition":null,"lowestRating":7,"conditionCategory":"good","structurallyDeficient":false,"operatingRating":5.4,"inventoryRating":3.3,"toll":false,"historical":"5","historicalName":"Not eligible","scourCritical":"N","detourKm":2,"status":"A","deckArea":4099.6}