{"id":"TX-7130002P0000000","structureNumber":"7130002P0000000","state":"TX","stateFips":"48","stateName":"Texas","countyFips":"043","placeFips":"00000","location":"7.82 Miles North of Panth","featuresIntersected":"TORNILLO CREEK","facilityCarried":"NORTH ENTRANCE ROA","lat":29.513889,"lon":-103.916667,"routePrefix":"6","routePrefixName":"Federal Lands","routeNumber":"11","owner":"66","ownerName":"National Park Service","functionalClass":"06","yearBuilt":1958,"yearReconstructed":1981,"material":"5","materialName":"Prestressed Concrete","materialGroup":"Prestressed Concrete","designType":"02","designTypeName":"Stringer/Multi-beam or Girder","lanesOn":2,"lanesUnder":0,"maxSpanM":1.8,"maxSpanFt":6.0,"lengthM":29.3,"lengthFt":96.2,"deckWidthM":1.0,"deckWidthFt":3.3,"roadwayWidthM":0.8,"adt":368,"adtYear":2022,"truckPct":3,"futureAdt":442,"deckCondition":"7","superstructureCondition":"6","substructureCondition":"7","culvertCondition":null,"channelCondition":"6","lowestRating":6,"conditionCategory":"fair","structurallyDeficient":false,"operatingRating":5.8,"inventoryRating":3.5,"toll":false,"historical":"5","historicalName":"Not eligible","scourCritical":"5","detourKm":199,"status":"A","deckArea":2990.6}