{"id":"ID-000000000014561","structureNumber":"000000000014561","state":"ID","stateFips":"16","stateName":"Idaho","countyFips":"073","placeFips":"00000","location":"15 S. MOUNTAIN HOME","featuresIntersected":"SNAKE RIVER","facilityCarried":"SH 51","lat":43.319444,"lon":-115.883333,"routePrefix":"3","routePrefixName":"State Highway","routeNumber":"51","owner":"01","ownerName":"State Highway Agency","functionalClass":"06","yearBuilt":2018,"yearReconstructed":null,"material":"5","materialName":"Prestressed Concrete","materialGroup":"Prestressed Concrete","designType":"02","designTypeName":"Stringer/Multi-beam or Girder","lanesOn":2,"lanesUnder":0,"maxSpanM":4.7,"maxSpanFt":15.5,"lengthM":19.2,"lengthFt":63.0,"deckWidthM":1.1,"deckWidthFt":3.6,"roadwayWidthM":1.0,"adt":2200,"adtYear":2022,"truckPct":5,"futureAdt":3300,"deckCondition":"8","superstructureCondition":"8","substructureCondition":"7","culvertCondition":null,"channelCondition":"8","lowestRating":7,"conditionCategory":"good","structurallyDeficient":false,"operatingRating":6.3,"inventoryRating":4.3,"toll":false,"historical":"4","historicalName":"Not determined","scourCritical":"8","detourKm":31,"status":"A","deckArea":2092.8}