{"id":"ID-000000000018465","structureNumber":"000000000018465","state":"ID","stateFips":"16","stateName":"Idaho","countyFips":"069","placeFips":"00000","location":"4 N. LAPWAI","featuresIntersected":"NPRR;CLEARWATER RIVER","facilityCarried":"US 95","lat":47.350833,"lon":-117.77,"routePrefix":"2","routePrefixName":"US Highway","routeNumber":"95","owner":"01","ownerName":"State Highway Agency","functionalClass":"02","yearBuilt":1962,"yearReconstructed":null,"material":"3","materialName":"Steel","materialGroup":"Steel","designType":"02","designTypeName":"Stringer/Multi-beam or Girder","lanesOn":2,"lanesUnder":0,"maxSpanM":3.7,"maxSpanFt":12.0,"lengthM":37.5,"lengthFt":123.0,"deckWidthM":1.0,"deckWidthFt":3.3,"roadwayWidthM":0.8,"adt":6200,"adtYear":2022,"truckPct":26,"futureAdt":9300,"deckCondition":"6","superstructureCondition":"5","substructureCondition":"6","culvertCondition":null,"channelCondition":"6","lowestRating":5,"conditionCategory":"fair","structurallyDeficient":false,"operatingRating":6.8,"inventoryRating":4.1,"toll":false,"historical":"4","historicalName":"Not determined","scourCritical":"8","detourKm":24,"status":"A","deckArea":3786.5}