{"id":"MO-1350","structureNumber":"1350","state":"MO","stateFips":"29","stateName":"Missouri","countyFips":"113","placeFips":"50204","location":"S 4 T 48 N R 1 E","featuresIntersected":"CUIVRE RVR","facilityCarried":"RT C E","lat":39.064167,"lon":-92.288333,"routePrefix":"3","routePrefixName":"State Highway","routeNumber":"C","owner":"01","ownerName":"State Highway Agency","functionalClass":"17","yearBuilt":1966,"yearReconstructed":2008,"material":"4","materialName":"Steel Continuous","materialGroup":"Steel","designType":"02","designTypeName":"Stringer/Multi-beam or Girder","lanesOn":2,"lanesUnder":0,"maxSpanM":4.1,"maxSpanFt":13.5,"lengthM":17.8,"lengthFt":58.4,"deckWidthM":0.9,"deckWidthFt":3.1,"roadwayWidthM":0.8,"adt":3504,"adtYear":2023,"truckPct":7,"futureAdt":7008,"deckCondition":"7","superstructureCondition":"4","substructureCondition":"7","culvertCondition":null,"channelCondition":"6","lowestRating":4,"conditionCategory":"poor","structurallyDeficient":true,"operatingRating":3.1,"inventoryRating":1.8,"toll":false,"historical":"5","historicalName":"Not eligible","scourCritical":"8","detourKm":27,"status":"P","deckArea":1655.4}