{"id":"MO-2771","structureNumber":"2771","state":"MO","stateFips":"29","stateName":"Missouri","countyFips":"023","placeFips":"06076","location":"S 13 T 26 N R 5 E","featuresIntersected":"BLACK RVR","facilityCarried":"US 67 S","lat":37.446944,"lon":-91.986944,"routePrefix":"2","routePrefixName":"US Highway","routeNumber":"67","owner":"01","ownerName":"State Highway Agency","functionalClass":"02","yearBuilt":1976,"yearReconstructed":null,"material":"4","materialName":"Steel Continuous","materialGroup":"Steel","designType":"02","designTypeName":"Stringer/Multi-beam or Girder","lanesOn":2,"lanesUnder":0,"maxSpanM":4.0,"maxSpanFt":13.0,"lengthM":26.0,"lengthFt":85.3,"deckWidthM":1.4,"deckWidthFt":4.7,"roadwayWidthM":1.3,"adt":4787,"adtYear":2023,"truckPct":24,"futureAdt":8377,"deckCondition":"6","superstructureCondition":"5","substructureCondition":"4","culvertCondition":null,"channelCondition":"5","lowestRating":4,"conditionCategory":"poor","structurallyDeficient":true,"operatingRating":4.6,"inventoryRating":2.7,"toll":false,"historical":"5","historicalName":"Not eligible","scourCritical":"5","detourKm":39,"status":"A","deckArea":3692.0}