{"id":"MO-3032","structureNumber":"3032","state":"MO","stateFips":"29","stateName":"Missouri","countyFips":"185","placeFips":"63092","location":"S 8 T 37 N R 26 W","featuresIntersected":"TRUMAN RESERVOIR","facilityCarried":"RT E S","lat":38.296667,"lon":-94.243056,"routePrefix":"3","routePrefixName":"State Highway","routeNumber":"E","owner":"01","ownerName":"State Highway Agency","functionalClass":"07","yearBuilt":1976,"yearReconstructed":2012,"material":"4","materialName":"Steel Continuous","materialGroup":"Steel","designType":"02","designTypeName":"Stringer/Multi-beam or Girder","lanesOn":2,"lanesUnder":0,"maxSpanM":5.2,"maxSpanFt":17.2,"lengthM":21.3,"lengthFt":69.9,"deckWidthM":0.9,"deckWidthFt":2.9,"roadwayWidthM":0.8,"adt":273,"adtYear":2023,"truckPct":11,"futureAdt":355,"deckCondition":"8","superstructureCondition":"7","substructureCondition":"7","culvertCondition":null,"channelCondition":"6","lowestRating":7,"conditionCategory":"good","structurallyDeficient":false,"operatingRating":3.2,"inventoryRating":1.9,"toll":false,"historical":"5","historicalName":"Not eligible","scourCritical":"8","detourKm":40,"status":"A","deckArea":1875.3}