{"id":"MO-8339","structureNumber":"8339","state":"MO","stateFips":"29","stateName":"Missouri","countyFips":"041","placeFips":"17776","location":"S 28 T 56 N R 21 W","featuresIntersected":"GRAND RVR","facilityCarried":"MO 139 S","lat":40.2425,"lon":-93.904167,"routePrefix":"3","routePrefixName":"State Highway","routeNumber":"139","owner":"01","ownerName":"State Highway Agency","functionalClass":"07","yearBuilt":1963,"yearReconstructed":null,"material":"4","materialName":"Steel Continuous","materialGroup":"Steel","designType":"03","designTypeName":"Girder and Floorbeam","lanesOn":2,"lanesUnder":0,"maxSpanM":5.5,"maxSpanFt":18.0,"lengthM":17.9,"lengthFt":58.9,"deckWidthM":0.8,"deckWidthFt":2.8,"roadwayWidthM":0.7,"adt":400,"adtYear":2023,"truckPct":16,"futureAdt":500,"deckCondition":"5","superstructureCondition":"6","substructureCondition":"6","culvertCondition":null,"channelCondition":"6","lowestRating":5,"conditionCategory":"fair","structurallyDeficient":false,"operatingRating":2.6,"inventoryRating":1.5,"toll":false,"historical":"5","historicalName":"Not eligible","scourCritical":"8","detourKm":103,"status":"A","deckArea":1525.8}