{"id":"NY-00000000106745C","structureNumber":"00000000106745C","state":"NY","stateFips":"36","stateName":"New York","countyFips":"005","placeFips":"51000","location":".1 MI S JCT I87 & I95","featuresIntersected":"RAMP C  HARLEM RIVER  ME","facilityCarried":"RTE I87","lat":41.958333,"lon":-75.449167,"routePrefix":"1","routePrefixName":"Interstate","routeNumber":"87","owner":"01","ownerName":"State Highway Agency","functionalClass":"11","yearBuilt":1976,"yearReconstructed":null,"material":"4","materialName":"Steel Continuous","materialGroup":"Steel","designType":"02","designTypeName":"Stringer/Multi-beam or Girder","lanesOn":1,"lanesUnder":1,"maxSpanM":3.8,"maxSpanFt":12.6,"lengthM":25.4,"lengthFt":83.2,"deckWidthM":0.9,"deckWidthFt":2.9,"roadwayWidthM":0.8,"adt":783,"adtYear":2020,"truckPct":8,"futureAdt":1000,"deckCondition":"5","superstructureCondition":"6","substructureCondition":"5","culvertCondition":null,"channelCondition":"7","lowestRating":5,"conditionCategory":"fair","structurallyDeficient":false,"operatingRating":5.4,"inventoryRating":3.0,"toll":false,"historical":"5","historicalName":"Not eligible","scourCritical":"5","detourKm":1,"status":"A","deckArea":2231.7}