{"id":"NY-000000005514539","structureNumber":"000000005514539","state":"NY","stateFips":"36","stateName":"New York","countyFips":"119","placeFips":"50617","location":"NEW ENGLAND VIADUCT","featuresIntersected":"WEBSTER AVENUE  METRO NO","facilityCarried":"RTE I95","lat":41.584444,"lon":-74.503611,"routePrefix":"1","routePrefixName":"Interstate","routeNumber":"95","owner":"31","ownerName":"State Toll Authority","functionalClass":"11","yearBuilt":1954,"yearReconstructed":1992,"material":"3","materialName":"Steel","materialGroup":"Steel","designType":"02","designTypeName":"Stringer/Multi-beam or Girder","lanesOn":6,"lanesUnder":4,"maxSpanM":4.0,"maxSpanFt":13.3,"lengthM":41.2,"lengthFt":135.2,"deckWidthM":2.9,"deckWidthFt":9.6,"roadwayWidthM":2.8,"adt":107326,"adtYear":2018,"truckPct":13,"futureAdt":181745,"deckCondition":"6","superstructureCondition":"5","substructureCondition":"5","culvertCondition":null,"channelCondition":null,"lowestRating":5,"conditionCategory":"fair","structurallyDeficient":false,"operatingRating":6.8,"inventoryRating":3.8,"toll":false,"historical":"4","historicalName":"Not determined","scourCritical":"N","detourKm":1,"status":"A","deckArea":12115.7}