{"id":"WI-B32007700000000","structureNumber":"B32007700000000","state":"WI","stateFips":"55","stateName":"Wisconsin","countyFips":"063","placeFips":"40775","location":"0.1M W JCT USH 53","featuresIntersected":"BLACK RIVER","facilityCarried":"CTH B / CLINTON ST","lat":44.620833,"lon":-91.529722,"routePrefix":"4","routePrefixName":"County Road","routeNumber":"B","owner":"01","ownerName":"State Highway Agency","functionalClass":"16","yearBuilt":1981,"yearReconstructed":null,"material":"6","materialName":"Prestressed Concrete Continuous","materialGroup":"Prestressed Concrete","designType":"02","designTypeName":"Stringer/Multi-beam or Girder","lanesOn":3,"lanesUnder":0,"maxSpanM":3.0,"maxSpanFt":9.9,"lengthM":18.2,"lengthFt":59.6,"deckWidthM":1.9,"deckWidthFt":6.1,"roadwayWidthM":1.6,"adt":7300,"adtYear":2021,"truckPct":null,"futureAdt":12200,"deckCondition":"7","superstructureCondition":"6","substructureCondition":"6","culvertCondition":null,"channelCondition":"8","lowestRating":6,"conditionCategory":"fair","structurallyDeficient":false,"operatingRating":4.6,"inventoryRating":2.8,"toll":false,"historical":"5","historicalName":"Not eligible","scourCritical":"5","detourKm":8,"status":"A","deckArea":3399.7}