{"total":13532,"good":7667,"fair":5264,"poor":601,"structurallyDeficient":601,"goodPct":56.7,"fairPct":38.9,"poorPct":4.4,"sdPct":4.4,"materials":{"Concrete":7030,"Prestressed Concrete":3527,"Steel":1929,"Wood/Timber":1022,"Metal (Other)":13,"Masonry":11},"designTypes":{"Culvert":6145,"Stringer/Multi-beam or Girder":4585,"Slab":1779,"Tee Beam":436,"Channel Beam":242,"Girder and Floorbeam":101,"Box Beam - Multiple":67,"Arch - Deck":51,"Frame":48,"Truss - Thru":44,"Segmental Box Girder":15,"Arch - Thru":7,"Truss - Deck":3,"Box Beam - Single/Spread":3,"Other":2,"Suspension":1,"Movable - Swing":1,"Movable - Bascule":1,"Movable - Lift":1},"ageDistribution":{"80+ years":918,"61-80 years":941,"41-60 years":4100,"21-40 years":4252,"0-20 years":3321},"owners":{"County Highway Agency":5388,"State Highway Agency":3693,"Town/Township":3514,"City/Municipal":711,"State Park/Forest":69,"U.S. Forest Service":61,"Local Park/Forest":19,"Private":19,"Other Local":12,"Bureau of Indian Affairs":11,"Railroad":10,"Fish and Wildlife":9,"Other State":8,"Corps of Engineers":5,"Tribal":2,"National Park Service":1},"avgAdt":4197,"totalDailyCrossings":56785237,"avgYearBuilt":1986,"oldestYear":1884,"newestYear":2023,"avgLengthFt":11.6,"ratingDistribution":{"0":7,"1":7,"2":10,"3":90,"4":487,"5":1906,"6":3358,"7":4431,"8":2936,"9":300},"state":"MN","stateName":"Minnesota","countyCount":87,"cityCount":2011,"topCounties":[{"fips":"053","total":936,"poor":38,"poorPct":4.1,"avgAdt":21933},{"fips":"137","total":663,"poor":45,"poorPct":6.8,"avgAdt":2679},{"fips":"109","total":365,"poor":5,"poorPct":1.4,"avgAdt":5412},{"fips":"045","total":348,"poor":10,"poorPct":2.9,"avgAdt":450},{"fips":"099","total":343,"poor":28,"poorPct":8.2,"avgAdt":1124},{"fips":"123","total":341,"poor":22,"poorPct":6.5,"avgAdt":23691},{"fips":"049","total":333,"poor":20,"poorPct":6.0,"avgAdt":2089},{"fips":"105","total":304,"poor":5,"poorPct":1.6,"avgAdt":606},{"fips":"119","total":268,"poor":9,"poorPct":3.4,"avgAdt":532},{"fips":"133","total":265,"poor":6,"poorPct":2.3,"avgAdt":772},{"fips":"037","total":259,"poor":4,"poorPct":1.5,"avgAdt":13263},{"fips":"169","total":237,"poor":11,"poorPct":4.6,"avgAdt":2250},{"fips":"083","total":234,"poor":7,"poorPct":3.0,"avgAdt":659},{"fips":"145","total":229,"poor":6,"poorPct":2.6,"avgAdt":5512},{"fips":"043","total":226,"poor":10,"poorPct":4.4,"avgAdt":496},{"fips":"027","total":225,"poor":13,"poorPct":5.8,"avgAdt":2608},{"fips":"173","total":218,"poor":6,"poorPct":2.8,"avgAdt":434},{"fips":"089","total":215,"poor":3,"poorPct":1.4,"avgAdt":245},{"fips":"127","total":200,"poor":21,"poorPct":10.5,"avgAdt":496},{"fips":"167","total":196,"poor":8,"poorPct":4.1,"avgAdt":373}],"worstBridges":[{"id":"MN-5767","state":"MN","stateName":"Minnesota","countyFips":"119","facilityCarried":"CSAH 1","featuresIntersected":"RED RIVER OF THE NORTH","location":"2.5 MI W OF JCT TH 75","lat":48.5625,"lon":-97.306389,"lowestRating":0,"yearBuilt":1939,"adt":205,"conditionCategory":"poor","structurallyDeficient":true,"materialName":"Steel","designTypeName":"Truss - Thru","lengthFt":36.2},{"id":"MN-638","state":"MN","stateName":"Minnesota","countyFips":"005","facilityCarried":"T 144","featuresIntersected":"TOAD RIVER","location":"0.3 MI E OF JCT TH 87","lat":47.049444,"lon":-96.408611,"lowestRating":0,"yearBuilt":1940,"adt":28,"conditionCategory":"poor","structurallyDeficient":true,"materialName":"Steel","designTypeName":"Stringer/Multi-beam or Girder","lengthFt":2.8},{"id":"MN-L2480","state":"MN","stateName":"Minnesota","countyFips":"039","facilityCarried":"T 115","featuresIntersected":"N BR MID FK ZUMBRO RIVER","location":"0.5 MI N OF JCT TH 57","lat":45.133056,"lon":-93.7775,"lowestRating":0,"yearBuilt":1930,"adt":14,"conditionCategory":"poor","structurallyDeficient":true,"materialName":"Steel","designTypeName":"Stringer/Multi-beam or Girder","lengthFt":3.0},{"id":"MN-L3942","state":"MN","stateName":"Minnesota","countyFips":"035","facilityCarried":"T 1331","featuresIntersected":"NOKASIPPI RIVER","location":"0.2 MI N OF JCT CSAH 2","lat":46.568333,"lon":-95.675,"lowestRating":0,"yearBuilt":1908,"adt":20,"conditionCategory":"poor","structurallyDeficient":true,"materialName":"Steel","designTypeName":"Truss - Thru","lengthFt":5.1},{"id":"MN-L4436","state":"MN","stateName":"Minnesota","countyFips":"069","facilityCarried":"T 310","featuresIntersected":"N BR TWO RIVERS","location":"0.3 MI E OF JCT CSAH 1","lat":50.1675,"lon":-97.7275,"lowestRating":0,"yearBuilt":1907,"adt":12,"conditionCategory":"poor","structurallyDeficient":true,"materialName":"Steel","designTypeName":"Truss - Thru","lengthFt":5.1},{"id":"MN-L5245","state":"MN","stateName":"Minnesota","countyFips":"063","facilityCarried":"T 187","featuresIntersected":"OKABENA CREEK","location":"0.3 MI S OF JCT CSAH 18","lat":45.260556,"lon":-96.938889,"lowestRating":0,"yearBuilt":1905,"adt":10,"conditionCategory":"poor","structurallyDeficient":true,"materialName":"Steel","designTypeName":"Truss - Thru","lengthFt":4.5},{"id":"MN-L5901","state":"MN","stateName":"Minnesota","countyFips":"049","facilityCarried":"M 12","featuresIntersected":"STREAM","location":"IN ZUMBROTA","lat":45.579167,"lon":-93.355278,"lowestRating":0,"yearBuilt":1935,"adt":60,"conditionCategory":"poor","structurallyDeficient":true,"materialName":"Steel","designTypeName":"Stringer/Multi-beam or Girder","lengthFt":2.2},{"id":"MN-64503","state":"MN","stateName":"Minnesota","countyFips":"127","facilityCarried":"CR 51","featuresIntersected":"REDWOOD RIVER","location":"0.9 MI S OF JCT CSAH 30","lat":45.745,"lon":-95.668333,"lowestRating":1,"yearBuilt":1962,"adt":15,"conditionCategory":"poor","structurallyDeficient":true,"materialName":"Wood or Timber","designTypeName":"Slab","lengthFt":7.8},{"id":"MN-7423","state":"MN","stateName":"Minnesota","countyFips":"061","facilityCarried":"UT 2233","featuresIntersected":"SWAN RIVER","location":"0.4 MI S OF JCT CSAH 10","lat":47.608611,"lon":-94.930556,"lowestRating":1,"yearBuilt":1917,"adt":25,"conditionCategory":"poor","structurallyDeficient":true,"materialName":"Concrete","designTypeName":"Arch - Deck","lengthFt":8.0},{"id":"MN-92697","state":"MN","stateName":"Minnesota","countyFips":"137","facilityCarried":"M 340","featuresIntersected":"STREAM","location":"0.1 MI W OF JCT CR444","lat":48.659722,"lon":-94.272222,"lowestRating":1,"yearBuilt":1968,"adt":20,"conditionCategory":"poor","structurallyDeficient":true,"materialName":"Steel","designTypeName":"Stringer/Multi-beam or Girder","lengthFt":2.5}],"mostTrafficked":[{"id":"MN-27V47","state":"MN","stateName":"Minnesota","countyFips":"053","facilityCarried":"I 35W","featuresIntersected":"MIDTOWN GREENWAY TRAIL","location":"1.3 MI S OF JCT TH 94","lat":44.985278,"lon":-94.043611,"adt":179358,"yearBuilt":2019,"lowestRating":8,"conditionCategory":"good","structurallyDeficient":false,"materialName":"Prestressed Concrete","designTypeName":"Stringer/Multi-beam or Girder","lengthFt":9.2},{"id":"MN-27415","state":"MN","stateName":"Minnesota","countyFips":"053","facilityCarried":"I 494","featuresIntersected":"KNOX AVE (BRT)","location":"0.18 MI W OF JCT I35W","lat":46.013889,"lon":-93.516944,"adt":177000,"yearBuilt":2021,"lowestRating":9,"conditionCategory":"good","structurallyDeficient":false,"materialName":"Concrete","designTypeName":"Culvert","lengthFt":4.8},{"id":"MN-27V38","state":"MN","stateName":"Minnesota","countyFips":"053","facilityCarried":"I 494","featuresIntersected":"TH 100","location":"AT THE JCT TH 100; 494","lat":45.728889,"lon":-93.365,"adt":175000,"yearBuilt":2003,"lowestRating":7,"conditionCategory":"good","structurallyDeficient":false,"materialName":"Steel","designTypeName":"Stringer/Multi-beam or Girder","lengthFt":20.6},{"id":"MN-27X11","state":"MN","stateName":"Minnesota","countyFips":"053","facilityCarried":"I 35W","featuresIntersected":"STORM SEWER","location":"I 35W NEAR 35TH ST","lat":45.593889,"lon":-94.069722,"adt":170406,"yearBuilt":2009,"lowestRating":9,"conditionCategory":"good","structurallyDeficient":false,"materialName":"Concrete","designTypeName":"Culvert","lengthFt":17.1},{"id":"MN-27X12","state":"MN","stateName":"Minnesota","countyFips":"053","facilityCarried":"I 35W","featuresIntersected":"STORM SEWER","location":"I 35W NEAR 39TH ST","lat":46.455,"lon":-94.065833,"adt":170406,"yearBuilt":2009,"lowestRating":8,"conditionCategory":"good","structurallyDeficient":false,"materialName":"Concrete","designTypeName":"Culvert","lengthFt":17.1},{"id":"MN-27891","state":"MN","stateName":"Minnesota","countyFips":"053","facilityCarried":"I 694","featuresIntersected":"TH 252; SB OFF RAMP","location":"AT THE JCT TH 252; 694","lat":45.348056,"lon":-93.5525,"adt":163000,"yearBuilt":1980,"lowestRating":5,"conditionCategory":"fair","structurallyDeficient":false,"materialName":"Steel Continuous","designTypeName":"Stringer/Multi-beam or Girder","lengthFt":17.1},{"id":"MN-9350","state":"MN","stateName":"Minnesota","countyFips":"053","facilityCarried":"I 94","featuresIntersected":"MISS R  ramp  W River Rd","location":"1.3 MI SE OF JCT TH 55","lat":46.566667,"lon":-94.143611,"adt":154000,"yearBuilt":1963,"lowestRating":6,"conditionCategory":"fair","structurallyDeficient":false,"materialName":"Steel Continuous","designTypeName":"Stringer/Multi-beam or Girder","lengthFt":100.1},{"id":"MN-27863","state":"MN","stateName":"Minnesota","countyFips":"053","facilityCarried":"I 94","featuresIntersected":"Cedar Ave","location":"0.2 MI E OF JCT TH 55","lat":46.528889,"lon":-94.626111,"adt":147000,"yearBuilt":1966,"lowestRating":5,"conditionCategory":"fair","structurallyDeficient":false,"materialName":"Steel Continuous","designTypeName":"Stringer/Multi-beam or Girder","lengthFt":17.0},{"id":"MN-27W18","state":"MN","stateName":"Minnesota","countyFips":"053","facilityCarried":"CON 715","featuresIntersected":"I 494","location":"0.6 MI W OF JCT TH 100","lat":45.794722,"lon":-94.37,"adt":145000,"yearBuilt":2017,"lowestRating":8,"conditionCategory":"good","structurallyDeficient":false,"materialName":"Steel Continuous","designTypeName":"Stringer/Multi-beam or Girder","lengthFt":35.4},{"id":"MN-62942","state":"MN","stateName":"Minnesota","countyFips":"123","facilityCarried":"I 35W","featuresIntersected":"COUNTY RD I","location":"2.8 MI N OF JCT TH 694","lat":45.895833,"lon":-93.686944,"adt":144000,"yearBuilt":2019,"lowestRating":8,"conditionCategory":"good","structurallyDeficient":false,"materialName":"Prestressed Concrete","designTypeName":"Stringer/Multi-beam or Girder","lengthFt":9.0}]}