{"id":"KS-999901700780941","structureNumber":"999901700780941","state":"KS","stateFips":"20","stateName":"Kansas","countyFips":"155","placeFips":"00000","location":"7.66 MI N KINGMAN COLN","featuresIntersected":"N. FORK NINNESCAH RIVER","facilityCarried":"K-14 HWY","lat":38.944444,"lon":-98.183333,"routePrefix":"3","routePrefixName":"State Highway","routeNumber":"14","owner":"01","ownerName":"State Highway Agency","functionalClass":"06","yearBuilt":1996,"yearReconstructed":null,"material":"6","materialName":"Prestressed Concrete Continuous","materialGroup":"Prestressed Concrete","designType":"02","designTypeName":"Stringer/Multi-beam or Girder","lanesOn":2,"lanesUnder":0,"maxSpanM":3.0,"maxSpanFt":9.8,"lengthM":20.2,"lengthFt":66.4,"deckWidthM":1.2,"deckWidthFt":3.8,"roadwayWidthM":1.1,"adt":1900,"adtYear":2022,"truckPct":12,"futureAdt":1938,"deckCondition":"7","superstructureCondition":"7","substructureCondition":"7","culvertCondition":null,"channelCondition":"7","lowestRating":7,"conditionCategory":"good","structurallyDeficient":false,"operatingRating":8.2,"inventoryRating":3.9,"toll":false,"historical":"5","historicalName":"Not eligible","scourCritical":"5","detourKm":39,"status":"A","deckArea":2347.8}