{"id":"PA-000000000007866","structureNumber":"000000000007866","state":"PA","stateFips":"42","stateName":"Pennsylvania","countyFips":"019","placeFips":"37344","location":"HARMONY NB","featuresIntersected":"PA 68 T-323 B&P RR & CRK","facilityCarried":"SR0079 NB","lat":40.969722,"lon":-80.240833,"routePrefix":"1","routePrefixName":"Interstate","routeNumber":"79","owner":"01","ownerName":"State Highway Agency","functionalClass":"01","yearBuilt":1962,"yearReconstructed":2005,"material":"4","materialName":"Steel Continuous","materialGroup":"Steel","designType":"03","designTypeName":"Girder and Floorbeam","lanesOn":2,"lanesUnder":6,"maxSpanM":5.8,"maxSpanFt":19.2,"lengthM":20.8,"lengthFt":68.3,"deckWidthM":1.1,"deckWidthFt":3.7,"roadwayWidthM":1.1,"adt":15360,"adtYear":2023,"truckPct":13,"futureAdt":21073,"deckCondition":"7","superstructureCondition":"5","substructureCondition":"6","culvertCondition":null,"channelCondition":"6","lowestRating":5,"conditionCategory":"fair","structurallyDeficient":false,"operatingRating":5.1,"inventoryRating":3.0,"toll":false,"historical":"5","historicalName":"Not eligible","scourCritical":"5","detourKm":1,"status":"A","deckArea":2373.5}