{"id":"PA-000000000005487","structureNumber":"000000000005487","state":"PA","stateFips":"42","stateName":"Pennsylvania","countyFips":"011","placeFips":"63624","location":"BUTTONWOOD ST. - READING","featuresIntersected":"SCH.R. 422 NSRC RIV.RD.","facilityCarried":"BUTTONWOOD STREET","lat":40.911944,"lon":-76.920556,"routePrefix":"5","routePrefixName":"City Street","routeNumber":"0","owner":"02","ownerName":"County Highway Agency","functionalClass":"19","yearBuilt":1932,"yearReconstructed":2014,"material":"1","materialName":"Concrete","materialGroup":"Concrete","designType":"11","designTypeName":"Arch - Deck","lanesOn":3,"lanesUnder":8,"maxSpanM":3.8,"maxSpanFt":12.3,"lengthM":23.5,"lengthFt":77.0,"deckWidthM":1.9,"deckWidthFt":6.3,"roadwayWidthM":1.3,"adt":14674,"adtYear":2020,"truckPct":1,"futureAdt":14791,"deckCondition":"6","superstructureCondition":"5","substructureCondition":"5","culvertCondition":null,"channelCondition":"7","lowestRating":5,"conditionCategory":"fair","structurallyDeficient":false,"operatingRating":10.0,"inventoryRating":6.2,"toll":false,"historical":"2","historicalName":"Eligible for NRHP","scourCritical":"5","detourKm":2,"status":"A","deckArea":4482.8}