{"id":"PA-000000000044099","structureNumber":"000000000044099","state":"PA","stateFips":"42","stateName":"Pennsylvania","countyFips":"027","placeFips":"58800","location":"3/4 MI E OF PINE SWAMP RD","featuresIntersected":"BIG POE CREEK","facilityCarried":"POE VALLEY ROAD","lat":42.089722,"lon":-78.67,"routePrefix":"7","routePrefixName":"State Lands","routeNumber":"0","owner":"11","ownerName":"State Park/Forest","functionalClass":"09","yearBuilt":2006,"yearReconstructed":null,"material":"7","materialName":"Wood or Timber","materialGroup":"Wood/Timber","designType":"10","designTypeName":"Truss - Thru","lanesOn":2,"lanesUnder":0,"maxSpanM":1,"maxSpanFt":3.2,"lengthM":1,"lengthFt":3.4,"deckWidthM":0.7,"deckWidthFt":2.1,"roadwayWidthM":0.6,"adt":100,"adtYear":2022,"truckPct":1,"futureAdt":135,"deckCondition":"8","superstructureCondition":"6","substructureCondition":"7","culvertCondition":null,"channelCondition":"7","lowestRating":6,"conditionCategory":"fair","structurallyDeficient":false,"operatingRating":6.4,"inventoryRating":4.4,"toll":false,"historical":"5","historicalName":"Not eligible","scourCritical":"8","detourKm":14,"status":"A","deckArea":67.6}