{"id":"PA-000000000004776","structureNumber":"000000000004776","state":"PA","stateFips":"42","stateName":"Pennsylvania","countyFips":"011","placeFips":"83928","location":"READING BYPASS","featuresIntersected":"THUN RECREATIONAL TRAIL","facilityCarried":"SR 422 (LR793)","lat":41.738889,"lon":-76.566389,"routePrefix":"2","routePrefixName":"US Highway","routeNumber":"422","owner":"01","ownerName":"State Highway Agency","functionalClass":"12","yearBuilt":1963,"yearReconstructed":1996,"material":"4","materialName":"Steel Continuous","materialGroup":"Steel","designType":"02","designTypeName":"Stringer/Multi-beam or Girder","lanesOn":4,"lanesUnder":0,"maxSpanM":3.7,"maxSpanFt":12.0,"lengthM":22.9,"lengthFt":75.3,"deckWidthM":2.0,"deckWidthFt":6.6,"roadwayWidthM":1.8,"adt":82168,"adtYear":2023,"truckPct":10,"futureAdt":89158,"deckCondition":"5","superstructureCondition":"5","substructureCondition":"4","culvertCondition":null,"channelCondition":null,"lowestRating":4,"conditionCategory":"poor","structurallyDeficient":true,"operatingRating":6.3,"inventoryRating":3.7,"toll":false,"historical":"5","historicalName":"Not eligible","scourCritical":"N","detourKm":3,"status":"A","deckArea":4590.0}