{"id":"MN-27880A","structureNumber":"27880A","state":"MN","stateFips":"27","stateName":"Minnesota","countyFips":"053","placeFips":"43000","location":"0.5 MI NE OF JCT TH 94","featuresIntersected":"3rd Street WB","facilityCarried":"CON 1098","lat":45.546667,"lon":-93.314722,"routePrefix":"1","routePrefixName":"Interstate","routeNumber":"1098","owner":"01","ownerName":"State Highway Agency","functionalClass":"11","yearBuilt":1970,"yearReconstructed":null,"material":"4","materialName":"Steel Continuous","materialGroup":"Steel","designType":"02","designTypeName":"Stringer/Multi-beam or Girder","lanesOn":1,"lanesUnder":17,"maxSpanM":3.4,"maxSpanFt":11.2,"lengthM":18.2,"lengthFt":59.7,"deckWidthM":0.9,"deckWidthFt":3.0,"roadwayWidthM":0.8,"adt":1500,"adtYear":1994,"truckPct":null,"futureAdt":1500,"deckCondition":"5","superstructureCondition":"6","substructureCondition":"5","culvertCondition":null,"channelCondition":null,"lowestRating":5,"conditionCategory":"fair","structurallyDeficient":false,"operatingRating":6.7,"inventoryRating":4.0,"toll":false,"historical":"5","historicalName":"Not eligible","scourCritical":"N","detourKm":null,"status":"A","deckArea":1638.9}