{"id":"OH-1811967","structureNumber":"1811967","state":"OH","stateFips":"39","stateName":"Ohio","countyFips":"035","placeFips":"09288","location":"0.25 MI. WEST OF I-71","featuresIntersected":"SR-291 & CSX RR","facilityCarried":"SNOW RD CR-87","lat":41.713889,"lon":-82.681111,"routePrefix":"4","routePrefixName":"County Road","routeNumber":"18072","owner":"01","ownerName":"State Highway Agency","functionalClass":"14","yearBuilt":1968,"yearReconstructed":null,"material":"4","materialName":"Steel Continuous","materialGroup":"Steel","designType":"07","designTypeName":"Frame","lanesOn":4,"lanesUnder":2,"maxSpanM":4.2,"maxSpanFt":13.7,"lengthM":26.8,"lengthFt":87.8,"deckWidthM":1.9,"deckWidthFt":6.4,"roadwayWidthM":1.6,"adt":28403,"adtYear":2015,"truckPct":7,"futureAdt":39423,"deckCondition":"5","superstructureCondition":"7","substructureCondition":"7","culvertCondition":null,"channelCondition":null,"lowestRating":5,"conditionCategory":"fair","structurallyDeficient":false,"operatingRating":3.2,"inventoryRating":2.3,"toll":false,"historical":"2","historicalName":"Eligible for NRHP","scourCritical":"N","detourKm":null,"status":"A","deckArea":5218.2}